{"createdBy":"areeb","updatedBy":"areeb","_id":"632991a558208b6fb01f0b65","id":"oxtLpcJPnX2rq7ErH9BfQ","name":"add table data in matrix","projectId":"6305eb4fb2d1671fbc4b1de8","gitBranchName":"Sprint-1","services":[{"_id":"632991a558208b6fb01f0b66","type":"1","command":{"responseHandler":[],"returns":[],"_id":"632991a558208b6fb01f0b67","attributes":{"nextWidgetId":"dynKdEqLuH0cZsBfOB7Dq","gridRadioValue":"","editableForm":false},"type":"3"}}],"createdAt":"20-Sep-2022","updatedAt":"20-Sep-2022","__v":0}