{"createdBy":"areeb","updatedBy":"areeb","_id":"63a16061137cd44b9ce4ae62","id":"kfpEviFKD5h5JQiEU8bX_","name":"delete authority matrix","projectId":"6305eb4fb2d1671fbc4b1de8","gitBranchName":"Sprint-1","services":[{"_id":"63a16061137cd44b9ce4ae63","type":"11","command":{"responseHandler":[],"returns":[],"_id":"63a16061137cd44b9ce4ae64","attributes":{"stateName":"description","storeType":"","selectedObjectBindingKey":"selectedObject","dataType":"","sourceBindingKey":""},"type":"3"}}],"createdAt":"20-Dec-2022","updatedAt":"20-Dec-2022","__v":0}