{"createdBy":"talha","updatedBy":"talha","_id":"63a8830821a0d87ea4ca2e63","projectId":"6305eb4fb2d1671fbc4b1de8","gitBranchName":"Sprint-1","name":"Edit Matrix Combinations","status":"ACTIVE","services":[{"_id":"63a88e1121a0d87ea4ca59f8","type":"2","command":{"responseHandler":[],"returns":[],"_id":"63a88e1121a0d87ea4ca59f9","attributes":{"triggers":[{"createdBy":"system","updatedBy":"system","_id":"633e75c035d5a10649dd048a","id":"C9VAY5AImRfVpeNy7py77","name":"Fill Form Data","projectType":"web","services":[{"_id":"61dd1cc511bed557b4cb0c89","type":"14","command":{"responseHandler":[],"returns":[],"_id":"61dd1cc511bed557b4cb0c99","attributes":{},"type":"2"}}],"createdAt":"11-Jan-2022","updatedAt":"11-Jan-2022","__v":0,"canRead":true},{"createdBy":"talha","updatedBy":"talha","_id":"63a88e0a21a0d87ea4ca587b","id":"nB2jBT_YnH_Hyf_6e8QII","name":"copy combinations from FORM to CS","projectId":"6305eb4fb2d1671fbc4b1de8","gitBranchName":"Sprint-1","services":[{"_id":"63a88e0a21a0d87ea4ca587c","type":"11","command":{"responseHandler":[],"returns":[],"_id":"63a88e0a21a0d87ea4ca587d","attributes":{"storeType":"","selectedObjectBindingKey":"selectedObject","dataType":"","destinationBindingKey":"combination","sourceBindingKey":"combination","sourceStoreType":1,"destinationStoreType":2,"targettedType":"array"},"type":"6"}}],"createdAt":"25-Dec-2022","updatedAt":"25-Dec-2022","__v":0}],"triggerIds":["C9VAY5AImRfVpeNy7py77","nB2jBT_YnH_Hyf_6e8QII"]},"type":"1"}}],"id":"wX3kUijpV9VV7NE0RB6pt","createdAt":"25-Dec-2022","updatedAt":"25-Dec-2022","__v":2}