{
  "id": "me_FsvX8S7FMK_i5lK4Uo",
  "_id": "e5M8HalMM5DgTND0J_aCZ",
  "projectId": "6475fc4c85cd1cddbc3b3524",
  "gitBranchName": "master",
  "name": "fetch title branchless accounts trigger",
  "old_name": "fetch title branchless accounts trigger",
  "status": "ACTIVE",
  "services": [
    {
      "type": "8",
      "command": {
        "type": "1",
        "attributes": {
          "loaderWidgetIds": [906070],
          "messageWidgetIds": [906070],
          "responseStateKey": "titleResponse",
          "url": "/branchless/account/get-title",
          "checksum": true,
          "encryption": true,
          "isDeviceDetails": true,
          "loginTrigger": false,
          "formData": false,
          "logoutTrigger": false,
          "headers": {
            "Content-Type": "application/json",
            "Accept": "application/json",
            "channel_key": "001",
            "CSRF_TOKEN": "4c6e939d-db00-4697-82d8-b69bb05aef5a",
            "locale": "en-ltr"
          },
          "requestBody": [
            {
              "type": 1,
              "name": "Form",
              "key": "branchlessAccNo",
              "value": "accountMobile"
            }
          ],
          "baseURL": "634555d068954540043d6820",
          "storeType": 2
        },
        "responseHandler": []
      }
    }
  ],
  "updatedAt": "6/7/2023",
  "createdAt": "6/7/2023",
  "createdBy": "telenor",
  "updatedBy": "telenor"
}
