{"createdBy":"talha","updatedBy":"talha","_id":"63adea1821a0d87ea4d531da","id":"97az5IM-WwaxKDd7wSKMV","name":"Map description","projectId":"63f349eda070071e283ca270","gitBranchName":"master","services":[{"_id":"63adea1821a0d87ea4d531db","type":"11","command":{"responseHandler":[],"returns":[],"_id":"63adea1821a0d87ea4d531dc","attributes":{"dataType":"value","destinationBindingKey":"description","sourceBindingKey":"selectedObject.payload.description","sourceStoreType":2,"destinationStoreType":1,"targettedType":"value"},"type":"6"}}],"createdAt":"30-Dec-2022","updatedAt":"30-Dec-2022","__v":0}