{"createdBy":"ahmarnew","updatedBy":"ahmerjavedkhan","_id":"63e0ee1b582f305450088f7e","id":"VXlRoCN6w39d9ENXqeNuU","name":"Map Bank User Status Binding Key","projectId":"6305eb4fb2d1671fbc4b1de8","gitBranchName":"Sprint-1","services":[{"_id":"63e0eee2582f305450089a45","type":"11","command":{"responseHandler":[],"returns":[],"_id":"63e0eee2582f305450089a46","attributes":{"requestBody":[],"storeType":"","selectedObjectBindingKey":"selectedObject","dataType":"object","destinationBindingKey":"status","sourceBindingKey":"selectedObject","sourceStoreType":2,"destinationStoreType":1,"filterList":[{"key":"code","changeValueConditonally":true,"logic":{"var":"currentScreen.selectedObject.status"}},{"key":"name","changeValueConditonally":true,"logic":{"var":"currentScreen.selectedObject.status"}}],"targettedType":"value"},"type":"6"}}],"createdAt":"06-Feb-2023","updatedAt":"06-Feb-2023","__v":1}