{"createdBy":"ahmerjavedkhan","updatedBy":"ahmerjavedkhan","_id":"63a4ab94137cd44b9cee6084","id":"6dqaJV_cJaj-WKY9jg8pa","name":"Swap FORGOT OTP TO LOGIN SCREEN","projectId":"6305eb4fb2d1671fbc4b1de8","gitBranchName":"Sprint-1","services":[{"_id":"63a4ab94137cd44b9cee6085","type":"1","command":{"responseHandler":[],"returns":[],"_id":"63a4ab94137cd44b9cee6086","attributes":{"fromWidgetId":"DfaACL2q3Wqa-sL2nKCNt","nextWidgetId":"Q8B5irzPhCEQ9AxZRnSzt","gridRadioValue":"Screen","selectedObjectBindingKey":"selectedObject","editableForm":false},"type":"2"}}],"createdAt":"23-Dec-2022","updatedAt":"23-Dec-2022","__v":0}