{
  "id": "oQviksSQuriasFAuMatKn",
  "_id": "bncNcmL822KwKKtu0NF7T",
  "projectId": "63f349eda070071e283ca270",
  "gitBranchName": "master",
  "name": "Tax Exemption Download",
  "old_name": "Tax Exemption Download",
  "status": "ACTIVE",
  "services": [
    {
      "type": "8",
      "command": {
        "type": "2",
        "attributes": {
          "loaderWidgetIds": [906070],
          "messageWidgetIds": [906070],
          "responseStateKey": "taxExemptionDoc",
          "url": "/corporate-registration/download-documents",
          "checksum": true,
          "encryption": true,
          "fileName": "Tax Exemption.pdf",
          "isDeviceDetails": true,
          "loginTrigger": false,
          "formData": false,
          "logoutTrigger": false,
          "headers": {
            "Content-Type": "application/json",
            "Accept": "application/json",
            "channel_key": "001",
            "CSRF_TOKEN": "4c6e939d-db00-4697-82d8-b69bb05aef5a",
            "locale": "en-ltr"
          },
          "requestBody": [
            {
              "type": 2,
              "name": "Current screen",
              "key": "document",
              "value": "corporateReg.data.soleProprietor.taxExemptionDocId"
            }
          ],
          "baseURL": "634555d068954540043d6820",
          "storeType": 2
        },
        "responseHandler": []
      }
    }
  ],
  "updatedAt": "5/17/2023",
  "createdAt": "5/17/2023",
  "createdBy": "ajk",
  "updatedBy": "ajk"
}
