{
  "id": "93En-Pkpe3V_7nSn95vXL",
  "_id": "_NMB9rSKOvBrAsaTGelhA",
  "projectId": "6475fc4c85cd1cddbc3b3524",
  "gitBranchName": "master",
  "name": "transactionRecordDetail Trigger",
  "old_name": "transactionRecordDetail Trigger",
  "status": "ACTIVE",
  "services": [
    {
      "type": "8",
      "command": {
        "type": "1",
        "attributes": {
          "loaderWidgetIds": [906070],
          "messageWidgetIds": [906070],
          "responseStateKey": "transactionRecordDetail",
          "url": "/report/corporate-payment-details/transaction-record-detail",
          "checksum": true,
          "encryption": true,
          "isDeviceDetails": true,
          "loginTrigger": false,
          "formData": false,
          "logoutTrigger": false,
          "headers": {
            "Content-Type": "application/json",
            "Accept": "application/json",
            "channel_key": "001",
            "CSRF_TOKEN": "4c6e939d-db00-4697-82d8-b69bb05aef5a",
            "locale": "en-ltr"
          },
          "requestBody": [
            {
              "type": 2,
              "name": "Current screen",
              "key": "corporateId",
              "value": "selectedObject.corporateId"
            },
            {
              "type": 2,
              "name": "Current screen",
              "key": "batchTransactionId",
              "value": "selectedObject.batchTransactionId"
            },
            {
              "type": 2,
              "name": "Current screen",
              "key": "batchTransactionRowId",
              "value": "selectedItem.id"
            }
          ],
          "baseURL": "634555d068954540043d6820",
          "storeType": 2
        },
        "responseHandler": []
      }
    }
  ],
  "csrf": "0.pgcimwasmsaNckTTwBMmfXNotjT07PdZ",
  "updatedAt": "1/30/2024",
  "createdAt": "1/30/2024",
  "createdBy": "masood",
  "updatedBy": "masood"
}
